Workbook

Sheet Summary
A1: Billing reconciliation: findings summary
A2: Period 01 Sep 2026 to 30 Sep 2026. Amounts exclude GST. Synthetic practice data, not a client result.
A4: Status | B4: Findings | C4: Hours | D4: Value ex GST
A5: Confirmed | B5: =COUNTIF(Register!$E$2:$E$12,A5) -> 2 | C5: =SUMIF(Register!$E$2:$E$12,A5,Register!$F$2:$F$12) -> 54 | D5: =SUMIF(Register!$E$2:$E$12,A5,Register!$G$2:$G$12) -> 4770
A6: Needs information | B6: =COUNTIF(Register!$E$2:$E$12,A6) -> 6 | C6: =SUMIF(Register!$E$2:$E$12,A6,Register!$F$2:$F$12) -> 57 | D6: =SUMIF(Register!$E$2:$E$12,A6,Register!$G$2:$G$12) -> 3950
A7: Explained | B7: =COUNTIF(Register!$E$2:$E$12,A7) -> 3 | C7: =SUMIF(Register!$E$2:$E$12,A7,Register!$F$2:$F$12) -> 100 | D7: =SUMIF(Register!$E$2:$E$12,A7,Register!$G$2:$G$12) -> 6500
A9: What each status means
A10: Confirmed: the records show the issue and the arithmetic is shown. Still worth a quick check with the job owner.
A11: Needs information: something doesn't tie and we can't conclude without an answer from you.
A12: Explained: looked like a gap, but a later invoice, an approved write-off or a matching amount accounts for it.
A13: Value is shown only where it can be defended from the records (for example unbilled hours × agreed rate).
A14: Fixed-fee overruns are margin lost, not an amount the customer owes.
A16: Control checks
A17: Check | B17: Result
A18: Hours: buckets add back to raw timesheet hours | B18: =IF(ABS('Hours bridge'!B12)<0.005,"PASS","FAIL") -> PASS
A19: Billing: buckets add back to raw invoice total | B19: =IF(ABS('Billing bridge'!B8)<0.005,"PASS","FAIL") -> PASS
A20: T&M jobs: every job's hours fully accounted for | B20: =IF(SUMPRODUCT(ABS('T&M jobs'!J2:J7))<0.005,"PASS","FAIL") -> PASS

Sheet Register
A1: Exception_ID | B1: Type | C1: Job_ID | D1: Client | E1: Status | F1: Hours | G1: Value_Ex_GST | H1: Evidence | I1: Calculation | J1: Next_question
A2: E001 | B2: UNATTRIBUTED_INVOICE | E2: Needs information | F2: 0 | G2: 2400 | H2: INV-3107 (invoice_lines.csv:10) | I2: Harbour Civil: $2,400.00 with no job reference | J2: Which job does this invoice belong to? Until we know, it can't explain any job's hours.
A3: E002 | B3: DUP_CREDIT | C3: J105 | D3: Redgum Developments | E3: Needs information | F3: 0 | G3: 500 | H3: CN-0040, CN-0041 | I3: Two credit notes for $500.00 on 29 Sep 2026; held in suspense, not deducted | J3: Was the customer meant to receive this credit twice?
A4: E003 | B4: UNBILLED | C4: J101 | D4: Harbour Civil | E4: Confirmed | F4: 24 | G4: 4320 | H4: Timesheets for J101; invoices INV-3101 | I4: 120 h approved billable − 96 h invoiced − 0 h invoiced later − 0 h written off = 24 h × $180 | J4: Is there an invoice we haven't seen, or was this time agreed as not chargeable?
A5: E004 | B5: BILLED_LATER | C5: J102 | D5: Northside Builders | E5: Explained | F5: 30 | G5: 4800 | H5: INV-3201 | I5: 30 h of September time invoiced on 08 Oct 2026 | J5: None. Timing difference only.
A6: E005 | B6: WRITE_OFF | C6: J103 | D6: Kestrel Water | E6: Explained | F6: 10 | G6: 1700 | H6: WO-0012 | I6: 10 h written off, approved by Owner: Goodwill: extra handover meeting | J6: None. Approved write-off.
A7: E006 | B7: INFERRED_HOURS | C7: J104 | D7: Lakeview Council Works | E7: Explained | F7: 60 | G7: 0 | H7: INV-3104 | I7: Invoice shows no hours: $9,000.00 ÷ $150 agreed rate = 60 h (medium confidence) | J7: Confirm the invoice was billed at the agreed rate.
A8: E007 | B8: RATE_DIFF | C8: J105 | D8: Redgum Developments | E8: Confirmed | F8: 30 | G8: 450 | H8: INV-3105 (invoice_lines.csv:8) | I8: 30 h × ($180 agreed − $165 invoiced) = $450.00 | J8: Was a discount agreed, or is the rate card out of date?
A9: E008 | B9: PENDING_TIME | C9: J106 | D9: Brindabella Energy | E9: Needs information | F9: 6 | G9: 1050 | H9: T0060 | I9: 6 h awaiting approval at period end; 6 h billable × $175 | J9: Will this time be approved and billed?
A10: E009 | B10: DUP_TIME | C10: J106 | D10: Brindabella Energy | E10: Needs information | F10: 3 | G10: 0 | H10: T0062 | I10: 1 entry identical to an earlier one (staff, date, job, hours, note); excluded from billable hours | J10: Is this a genuine second piece of work or a double entry?
A11: E010 | B11: ORPHAN_TIME | C11: J199 | E11: Needs information | F11: 8 | G11: 0 | H11: T0063, T0064 | I11: 8 h booked to J199, which is not in the job list | J11: Which job should this time be on?
A12: E011 | B12: MARGIN_EROSION | C12: F201 | D12: Harbour Civil | E12: Needs information | F12: 40 | G12: 0 | H12: Timesheets for F201 | I12: 220 h before + 120 h this period = 340 h against a 300 h budget | J12: Margin lost, not an amount the customer owes. Was a variation agreed for the extra work?

Sheet T&M jobs
A1: Job_ID | B1: Client | C1: Agreed_Rate | D1: Logged_Billable_Hours | E1: Billed_In_Period | F1: Billed_Later | G1: Written_Off_Approved | H1: Unbilled | I1: Over_Billed | J1: Check (should be 0)
A2: J101 | B2: Harbour Civil | C2: 180 | D2: 120 | E2: 96 | F2: 0 | G2: 0 | H2: 24 | I2: 0 | J2: =D2-E2-F2-G2-H2 -> 0
A3: J102 | B3: Northside Builders | C3: 160 | D3: 80 | E3: 50 | F3: 30 | G3: 0 | H3: 0 | I3: 0 | J3: =D3-E3-F3-G3-H3 -> 0
A4: J103 | B4: Kestrel Water | C4: 170 | D4: 70 | E4: 60 | F4: 0 | G4: 10 | H4: 0 | I4: 0 | J4: =D4-E4-F4-G4-H4 -> 0
A5: J104 | B5: Lakeview Council Works | C5: 150 | D5: 60 | E5: 60 | F5: 0 | G5: 0 | H5: 0 | I5: 0 | J5: =D5-E5-F5-G5-H5 -> 0
A6: J105 | B6: Redgum Developments | C6: 180 | D6: 30 | E6: 30 | F6: 0 | G6: 0 | H6: 0 | I6: 0 | J6: =D6-E6-F6-G6-H6 -> 0
A7: J106 | B7: Brindabella Energy | C7: 175 | D7: 43 | E7: 43 | F7: 0 | G7: 0 | H7: 0 | I7: 0 | J7: =D7-E7-F7-G7-H7 -> 0
A9: Each row: logged approved billable hours = billed in period + billed later + approved write-offs + unbilled. Over-billed shown separately.

Sheet Fixed-fee jobs
A1: Job_ID | B1: Client | C1: Fee_Ex_GST | D1: Budget_Hours | E1: Hours_Before_Period | F1: Period_Hours | G1: Cumulative hours | H1: Over budget (hours) | I1: Budget used
A2: F201 | B2: Harbour Civil | C2: 48000 | D2: 300 | E2: 220 | F2: 120 | G2: =E2+F2 -> 340 | H2: =MAX(0,G2-D2) -> 40 | I2: =IF(D2=0,0,G2/D2) -> 1.1333333
A3: F202 | B3: Kestrel Water | C3: 30000 | D3: 200 | E3: 80 | F3: 60 | G3: =E3+F3 -> 140 | H3: =MAX(0,G3-D3) -> 0 | I3: =IF(D3=0,0,G3/D3) -> 0.7
A4: F203 | B4: Redgum Developments | C4: 24000 | D4: 150 | E4: 100 | F4: 45 | G4: =E4+F4 -> 145 | H4: =MAX(0,G4-D4) -> 0 | I4: =IF(D4=0,0,G4/D4) -> 0.96666667
A5: F204 | B5: Northside Builders | C5: 16000 | D5: 100 | E5: 0 | F5: 30 | G5: =E5+F5 -> 30 | H5: =MAX(0,G5-D5) -> 0 | I5: =IF(D5=0,0,G5/D5) -> 0.3
A7: Hours over budget on a fixed fee are margin lost. They are not an amount the customer owes unless a variation was agreed.

Sheet Hours bridge
A1: Bucket | B1: Hours
A2: Approved billable (T&M) | B2: 403
A3: Approved billable (fixed fee) | B3: 240
A4: Approved non-billable | B4: 25
A5: Duplicate entry | B5: 3
A6: Out of period | B6: 5
A7: Pending approval | B7: 6
A8: Rejected | B8: 4
A9: Unknown job code | B9: 8
A10: Total of buckets | B10: =SUM(B2:B9) -> 694
A11: Raw timesheet hours (as exported) | B11: 694
A12: Difference (must be 0) | B12: =B10-B11 -> 0

Sheet Billing bridge
A1: Bucket | B1: Amount ex GST
A2: Issued after period (look-ahead) | B2: 4800
A3: Issued in period | B3: 91955
A4: No job reference | B4: 2400
A5: Void | B5: 12800
A6: Total of buckets | B6: =SUM(B2:B5) -> 111955
A7: Raw invoice lines (as exported) | B7: 111955
A8: Difference (must be 0) | B8: =B6-B7 -> 0

Sheet Assumptions
A1: Reporting period | B1: 01 Sep 2026 to 30 Sep 2026
A2: Look-ahead window | B2: Invoices issued up to 31 days after period end are treated as billing period hours (assumption: confirm with client)
A3: Matching tolerance | B3: 0.25 hours
A4: Hours on invoices without hours | B4: Amount ÷ agreed rate (medium confidence)
A5: Duplicates | B5: Same staff, date, job, hours and note as an earlier entry
A6: Write-offs | B6: Count as explained only if an approver is recorded
A7: Credit notes | B7: Same job, date and amount as another: second one held in suspense, not deducted
A8: GST | B8: All amounts exclude GST. No tax or GST conclusions are drawn.
